.gitignore
CHANGELOG.md
LICENSE
README.md
logo.png
pyproject.toml
setup.py
uv.lock
.github/workflows/python-tests.yml
src/open_ephys/__init__.py
src/open_ephys/analysis/README.md
src/open_ephys/analysis/__init__.py
src/open_ephys/analysis/py.typed
src/open_ephys/analysis/recording.py
src/open_ephys/analysis/recordnode.py
src/open_ephys/analysis/session.py
src/open_ephys/analysis/utils.py
src/open_ephys/analysis/formats/BinaryRecording.py
src/open_ephys/analysis/formats/NwbRecording.py
src/open_ephys/analysis/formats/OpenEphysRecording.py
src/open_ephys/analysis/formats/__init__.py
src/open_ephys/analysis/formats/oebin_schema.json
src/open_ephys/analysis/formats/helpers/__init__.py
src/open_ephys/analysis/formats/helpers/oe_fast_loader.py
src/open_ephys/control/README.md
src/open_ephys/control/__init__.py
src/open_ephys/control/http_server.py
src/open_ephys/control/network_control.py
src/open_ephys/streaming/README.md
src/open_ephys/streaming/__init__.py
src/open_ephys/streaming/event_listener.py
src/open_ephys_python_tools.egg-info/PKG-INFO
src/open_ephys_python_tools.egg-info/SOURCES.txt
src/open_ephys_python_tools.egg-info/dependency_links.txt
src/open_ephys_python_tools.egg-info/requires.txt
src/open_ephys_python_tools.egg-info/top_level.txt
tests/test_binary_format.py
tests/test_nwb_format.py
tests/test_openephys_format.py
tests/data/v0.6.7_Binary/Record Node 101/settings.xml
tests/data/v0.6.7_Binary/Record Node 101/experiment1/recording1/structure.oebin
tests/data/v0.6.7_Binary/Record Node 101/experiment1/recording1/sync_messages.txt
tests/data/v0.6.7_Binary/Record Node 101/experiment1/recording1/continuous/File_Reader-100.example_data/continuous.dat
tests/data/v0.6.7_Binary/Record Node 101/experiment1/recording1/continuous/File_Reader-100.example_data/sample_numbers.npy
tests/data/v0.6.7_Binary/Record Node 101/experiment1/recording1/continuous/File_Reader-100.example_data/timestamps.npy
tests/data/v0.6.7_Binary/Record Node 101/experiment1/recording1/events/File_Reader-100.example_data/TTL/full_words.npy
tests/data/v0.6.7_Binary/Record Node 101/experiment1/recording1/events/File_Reader-100.example_data/TTL/sample_numbers.npy
