Metadata-Version: 2.4
Name: open-ephys-python-tools
Version: 1.0.0
Summary: Software tools for interfacing with the Open Ephys GUI
License: MIT
Classifier: Programming Language :: Python :: 3
Classifier: License :: OSI Approved :: MIT License
Classifier: Operating System :: OS Independent
Requires-Python: >=3.9
License-File: LICENSE
Requires-Dist: numpy
Requires-Dist: pandas
Requires-Dist: h5py
Requires-Dist: zmq
Requires-Dist: requests
Dynamic: license-file
